README.md
setup.py
pyrorl/__init__.py
pyrorl.egg-info/PKG-INFO
pyrorl.egg-info/SOURCES.txt
pyrorl.egg-info/dependency_links.txt
pyrorl.egg-info/requires.txt
pyrorl.egg-info/top_level.txt
pyrorl/envs/__init__.py
pyrorl/envs/pyrorl.py
pyrorl/envs/environment/__init__.py
pyrorl/envs/environment/environment.py
pyrorl/envs/environment/environment_constant.py
pyrorl/envs/map_helpers/__init__.py
pyrorl/envs/map_helpers/create_map_info.py
pyrorl/map_helpers/__init__.py
pyrorl/map_helpers/create_map_info.py