Metadata-Version: 2.1
Name: pyrorl
Version: 1.0.0
Summary: An RL Environment for Wildfire Evacuation
Home-page: https://sisl.github.io/PyroRL/
Author: Stanford Intelligent Systems Laboratory
License: UNKNOWN
Platform: UNKNOWN
Classifier: Programming Language :: Python :: 3
Classifier: License :: OSI Approved :: MIT License
Classifier: Operating System :: OS Independent
